[
  {
    "id": "386556286186",
    "name": "مصنع راتنجات الخليج للراتنجات الصناعية",
    "domain": "msn.com",
    "cr": "1011014128.0",
    "phone": "966567634444"
  },
  {
    "id": "385694346434",
    "name": "مصنع شركة سيل الريادة الصناعية السعودية",
    "domain": "msn.com",
    "cr": "1011139291.0",
    "phone": "966565551100"
  },
  {
    "id": "386611611840",
    "name": "مصنع موسى غيث موسى الغيث للصناعة",
    "domain": "msn.com",
    "cr": "2511025117.0",
    "phone": "966555553977"
  },
  {
    "id": "386583269568",
    "name": "مصنع تلال أجـا للصناعة",
    "domain": "msn.com",
    "cr": "3350043454.0",
    "phone": "966503387213"
  },
  {
    "id": "385775922404",
    "name": "مصنع نبأ للبلاستيك",
    "domain": "msn.com",
    "cr": "4030141996.0",
    "phone": "548881598"
  },
  {
    "id": "385802903781",
    "name": "المصنع الالى للالمنيوم للصناعة",
    "domain": "msn.com",
    "cr": "1010149732.0",
    "phone": "551556344"
  },
  {
    "id": "386522096857",
    "name": "مصنع اوائل البنائين لصناعة المواد الانشائية",
    "domain": "msn.com",
    "cr": "4030012453.0",
    "phone": "505244555"
  },
  {
    "id": "299332801778",
    "name": "Kenoz al fan for marble and decoration industry\ncompany Manufacturer",
    "domain": "aol.com",
    "cr": null,
    "phone": "+1 800-290-4726"
  }
]